README.md
setup.py
splunk_hec_stream/__init__.py
splunk_hec_stream/firehose_processor.py
splunk_hec_stream/logging.py
splunk_hec_stream.egg-info/PKG-INFO
splunk_hec_stream.egg-info/SOURCES.txt
splunk_hec_stream.egg-info/dependency_links.txt
splunk_hec_stream.egg-info/top_level.txt