Metadata-Version: 2.1
Name: splunk-hec-stream
Version: 0.3
Summary: Splunk HEC Stream
Home-page: https://github.com/shuichiro-makigaki/splunk_hec_stream
Author: Shuichiro MAKIGAKI
Author-email: shuichiro.makigaki@gmail.com
License: MIT License
Platform: UNKNOWN
